llama_cleanup/__init__.py
llama_cleanup/data_loader.py
llama_cleanup/fuzzy_match.py
llama_cleanup/geo_location.py
llama_cleanup/main.py
llama_cleanup/model_invoke.py
llama_cleanup/scrape.py
llama_cleanup/spell_checker.py
llama_cleanup/utils.py
llama_cleanup/optional_files/clean_address_transformer_model.zip
llama_cleanup/optional_files/mappings.json
llama_cleanup/optional_files/tokenizer/special_tokens_map.json
llama_cleanup/optional_files/tokenizer/tokenizer_config.json
llama_cleanup/optional_files/tokenizer/vocab.txt
llama_cleanup-2.1.0.dist-info/METADATA
llama_cleanup-2.1.0.dist-info/WHEEL
llama_cleanup-2.1.0.dist-info/entry_points.txt
llama_cleanup-2.1.0.dist-info/top_level.txt
llama_cleanup-2.1.0.dist-info/RECORD
