Metadata-Version: 2.1
Name: llama-cleanup
Version: 2.1.0
Summary: A package to process addresses and filter out noise
Home-page: https://github.com/AndrewGordienko/address-cleanup
Author: Andrew
Author-email: gordienko.adg@gmail.com
Classifier: Programming Language :: Python :: 3
Classifier: License :: OSI Approved :: MIT License
Classifier: Operating System :: OS Independent
Requires-Python: >=3.8
Requires-Dist: pandas
Requires-Dist: langchain-ollama
Provides-Extra: all
